[
    {
        "company": "Maggio, Cronin and Donnelly",
        "position": "Executive Secretary",
        "jobLocation": "Gaspar",
        "jobType": "full-time",
        "status": "pending",
        "createdBy": "6277c5c549827787d8250ed2",
        "createdAt": "2019-12-31T13:22:15Z"
    },
    {
        "company": "Kulas Group",
        "position": "Accountant III",
        "jobLocation": "Gombangan",
        "jobType": "part-time",
        "status": "interview",
        "createdBy": "6277c5c549827787d8250ed2",
        "createdAt": "2022-05-02T18:05:13Z"
    },
    {
        "company": "Daniel and Sons",
        "position": "Social Worker",
        "jobLocation": "Złotniki Kujawskie",
        "jobType": "full-time",
        "status": "pending",
        "createdBy": "6277c5c549827787d8250ed2",
        "createdAt": "2019-06-17T12:55:54Z"
    },
    {
        "company": "Becker, Lang and Sanford",
        "position": "Account Executive",
        "jobLocation": "El Mida",
        "jobType": "full-time",
        "status": "interview",
        "createdBy": "6277c5c549827787d8250ed2",
        "createdAt": "2020-06-14T09:52:19Z"
    },
    {
        "company": "Goodwin, Corwin and Rogahn",
        "position": "Recruiter",
        "jobLocation": "Depapre",
        "jobType": "remote",
        "status": "interview",
        "createdBy": "6277c5c549827787d8250ed2",
        "createdAt": "2021-01-21T08:38:38Z"
    },
    {
        "company": "Torp and Sons",
        "position": "Staff Accountant IV",
        "jobLocation": "Tiyingtali Kelod",
        "jobType": "full-time",
        "status": "interview",
        "createdBy": "6277c5c549827787d8250ed2",
        "createdAt": "2020-10-07T16:10:53Z"
    },
    {
        "company": "Kertzmann-Gleichner",
        "position": "Human Resources Manager",
        "jobLocation": "Stuttgart Stuttgart-Mitte",
        "jobType": "internship",
        "status": "interview",
        "createdBy": "6277c5c549827787d8250ed2",
        "createdAt": "2022-03-08T09:53:11Z"
    },
    {
        "company": "Crist, Dibbert and Nitzsche",
        "position": "Systems Administrator IV",
        "jobLocation": "Pedregulho",
        "jobType": "internship",
        "status": "declined",
        "createdBy": "6277c5c549827787d8250ed2",
        "createdAt": "2022-01-02T04:08:05Z"
    },
    {
        "company": "McDermott-Emmerich",
        "position": "Social Worker",
        "jobLocation": "Bangil",
        "jobType": "part-time",
        "status": "pending",
        "createdBy": "6277c5c549827787d8250ed2",
        "createdAt": "2019-10-16T15:01:08Z"
    },
    {
        "company": "Stoltenberg, Romaguera and Bayer",
        "position": "Technical Writer",
        "jobLocation": "Rzhavki",
        "jobType": "part-time",
        "status": "pending",
        "createdBy": "6277c5c549827787d8250ed2",
        "createdAt": "2020-06-22T04:25:29Z"
    },
    {
        "company": "Hand, Stark and Barrows",
        "position": "Environmental Specialist",
        "jobLocation": "Khōst",
        "jobType": "remote",
        "status": "interview",
        "createdBy": "6277c5c549827787d8250ed2",
        "createdAt": "2021-04-08T02:41:54Z"
    },
    {
        "company": "Klein Group",
        "position": "Nuclear Power Engineer",
        "jobLocation": "Caburan",
        "jobType": "internship",
        "status": "pending",
        "createdBy": "6277c5c549827787d8250ed2",
        "createdAt": "2022-03-31T15:43:51Z"
    },
    {
        "company": "Lang-Pagac",
        "position": "Tax Accountant",
        "jobLocation": "San Miguel",
        "jobType": "part-time",
        "status": "interview",
        "createdBy": "6277c5c549827787d8250ed2",
        "createdAt": "2020-08-29T20:17:52Z"
    },
    {
        "company": "Flatley, Bogan and McCullough",
        "position": "VP Quality Control",
        "jobLocation": "Macapsing",
        "jobType": "internship",
        "status": "pending",
        "createdBy": "6277c5c549827787d8250ed2",
        "createdAt": "2020-07-13T07:44:39Z"
    },
    {
        "company": "Rosenbaum, Johns and Mertz",
        "position": "Data Coordiator",
        "jobLocation": "Ḩabīl al Jabr",
        "jobType": "full-time",
        "status": "interview",
        "createdBy": "6277c5c549827787d8250ed2",
        "createdAt": "2020-03-05T03:27:33Z"
    },
    {
        "company": "Strosin Inc",
        "position": "Junior Executive",
        "jobLocation": "Hepu",
        "jobType": "remote",
        "status": "pending",
        "createdBy": "6277c5c549827787d8250ed2",
        "createdAt": "2020-03-10T15:33:39Z"
    },
    {
        "company": "Mayer, Rohan and Goodwin",
        "position": "Accountant IV",
        "jobLocation": "Barra de São Francisco",
        "jobType": "remote",
        "status": "declined",
        "createdBy": "6277c5c549827787d8250ed2",
        "createdAt": "2022-01-17T21:39:48Z"
    },
    {
        "company": "Pouros-Ritchie",
        "position": "Community Outreach Specialist",
        "jobLocation": "Topeka",
        "jobType": "remote",
        "status": "declined",
        "createdBy": "6277c5c549827787d8250ed2",
        "createdAt": "2021-02-05T00:18:42Z"
    },
    {
        "company": "Hamill-Huel",
        "position": "Senior Cost Accountant",
        "jobLocation": "Kristianstad",
        "jobType": "full-time",
        "status": "declined",
        "createdBy": "6277c5c549827787d8250ed2",
        "createdAt": "2020-09-28T16:55:20Z"
    },
    {
        "company": "Ward, Kiehn and Kihn",
        "position": "Structural Engineer",
        "jobLocation": "Salavan",
        "jobType": "internship",
        "status": "pending",
        "createdBy": "6277c5c549827787d8250ed2",
        "createdAt": "2019-11-04T03:15:53Z"
    },
    {
        "company": "Pacocha-Metz",
        "position": "Account Coordinator",
        "jobLocation": "Juigalpa",
        "jobType": "internship",
        "status": "pending",
        "createdBy": "6277c5c549827787d8250ed2",
        "createdAt": "2019-07-04T15:51:15Z"
    },
    {
        "company": "Dach, Gislason and Rice",
        "position": "Information Systems Manager",
        "jobLocation": "Ladhewāla Warāich",
        "jobType": "remote",
        "status": "declined",
        "createdBy": "6277c5c549827787d8250ed2",
        "createdAt": "2020-08-18T09:38:35Z"
    },
    {
        "company": "Moore Group",
        "position": "Operator",
        "jobLocation": "Borovskiy",
        "jobType": "full-time",
        "status": "declined",
        "createdBy": "6277c5c549827787d8250ed2",
        "createdAt": "2019-08-09T10:23:40Z"
    },
    {
        "company": "Kulas and Sons",
        "position": "Social Worker",
        "jobLocation": "Ulset",
        "jobType": "remote",
        "status": "interview",
        "createdBy": "6277c5c549827787d8250ed2",
        "createdAt": "2021-11-20T10:34:40Z"
    },
    {
        "company": "Murphy LLC",
        "position": "Structural Analysis Engineer",
        "jobLocation": "Saipan",
        "jobType": "internship",
        "status": "interview",
        "createdBy": "6277c5c549827787d8250ed2",
        "createdAt": "2019-06-30T02:15:56Z"
    },
    {
        "company": "Ziemann, Volkman and Reichel",
        "position": "Teacher",
        "jobLocation": "Wang Hin",
        "jobType": "remote",
        "status": "interview",
        "createdBy": "6277c5c549827787d8250ed2",
        "createdAt": "2021-09-03T21:18:10Z"
    },
    {
        "company": "Armstrong Inc",
        "position": "Internal Auditor",
        "jobLocation": "Makumbako",
        "jobType": "full-time",
        "status": "pending",
        "createdBy": "6277c5c549827787d8250ed2",
        "createdAt": "2021-09-15T15:52:22Z"
    },
    {
        "company": "Feil-Lindgren",
        "position": "Civil Engineer",
        "jobLocation": "Bulubrangsi",
        "jobType": "part-time",
        "status": "interview",
        "createdBy": "6277c5c549827787d8250ed2",
        "createdAt": "2020-07-12T04:24:04Z"
    },
    {
        "company": "Stoltenberg-Strosin",
        "position": "Health Coach II",
        "jobLocation": "Little Rock",
        "jobType": "remote",
        "status": "declined",
        "createdBy": "6277c5c549827787d8250ed2",
        "createdAt": "2019-12-24T07:51:41Z"
    },
    {
        "company": "Braun-Kshlerin",
        "position": "Community Outreach Specialist",
        "jobLocation": "Nykvarn",
        "jobType": "part-time",
        "status": "declined",
        "createdBy": "6277c5c549827787d8250ed2",
        "createdAt": "2022-04-26T10:43:18Z"
    },
    {
        "company": "Pfannerstill-Jerde",
        "position": "GIS Technical Architect",
        "jobLocation": "Corujeira",
        "jobType": "full-time",
        "status": "pending",
        "createdBy": "6277c5c549827787d8250ed2",
        "createdAt": "2020-07-07T20:13:04Z"
    },
    {
        "company": "Runolfsdottir Inc",
        "position": "Product Engineer",
        "jobLocation": "Sharm el-Sheikh",
        "jobType": "internship",
        "status": "pending",
        "createdBy": "6277c5c549827787d8250ed2",
        "createdAt": "2021-03-16T11:41:53Z"
    },
    {
        "company": "Lindgren-Treutel",
        "position": "Mechanical Systems Engineer",
        "jobLocation": "San Gregorio",
        "jobType": "remote",
        "status": "pending",
        "createdBy": "6277c5c549827787d8250ed2",
        "createdAt": "2022-03-05T16:14:36Z"
    },
    {
        "company": "Dach Inc",
        "position": "Assistant Manager",
        "jobLocation": "Nampicuan",
        "jobType": "part-time",
        "status": "interview",
        "createdBy": "6277c5c549827787d8250ed2",
        "createdAt": "2021-12-04T06:55:03Z"
    },
    {
        "company": "Breitenberg-Ruecker",
        "position": "Compensation Analyst",
        "jobLocation": "Susanino",
        "jobType": "part-time",
        "status": "pending",
        "createdBy": "6277c5c549827787d8250ed2",
        "createdAt": "2020-01-05T07:23:23Z"
    },
    {
        "company": "Wyman Inc",
        "position": "Account Representative III",
        "jobLocation": "Kabin Buri",
        "jobType": "full-time",
        "status": "pending",
        "createdBy": "6277c5c549827787d8250ed2",
        "createdAt": "2021-11-18T20:28:45Z"
    },
    {
        "company": "Franecki, Lind and Runte",
        "position": "Financial Advisor",
        "jobLocation": "Kibonsod",
        "jobType": "internship",
        "status": "interview",
        "createdBy": "6277c5c549827787d8250ed2",
        "createdAt": "2019-08-15T16:43:49Z"
    },
    {
        "company": "Ziemann Group",
        "position": "Quality Engineer",
        "jobLocation": "Pital",
        "jobType": "internship",
        "status": "declined",
        "createdBy": "6277c5c549827787d8250ed2",
        "createdAt": "2019-09-02T15:35:34Z"
    },
    {
        "company": "Rath Group",
        "position": "VP Quality Control",
        "jobLocation": "Vinež",
        "jobType": "internship",
        "status": "interview",
        "createdBy": "6277c5c549827787d8250ed2",
        "createdAt": "2019-06-15T22:08:10Z"
    },
    {
        "company": "Harber-Fisher",
        "position": "Pharmacist",
        "jobLocation": "Sanshui",
        "jobType": "internship",
        "status": "pending",
        "createdBy": "6277c5c549827787d8250ed2",
        "createdAt": "2022-01-04T00:11:58Z"
    },
    {
        "company": "Gulgowski-Klein",
        "position": "VP Sales",
        "jobLocation": "Loppi",
        "jobType": "remote",
        "status": "declined",
        "createdBy": "6277c5c549827787d8250ed2",
        "createdAt": "2020-06-09T03:19:25Z"
    },
    {
        "company": "Rowe Group",
        "position": "Clinical Specialist",
        "jobLocation": "Laironja",
        "jobType": "remote",
        "status": "interview",
        "createdBy": "6277c5c549827787d8250ed2",
        "createdAt": "2021-04-02T02:18:20Z"
    },
    {
        "company": "Howe-Ritchie",
        "position": "General Manager",
        "jobLocation": "Zhenlong",
        "jobType": "remote",
        "status": "pending",
        "createdBy": "6277c5c549827787d8250ed2",
        "createdAt": "2020-06-18T18:24:19Z"
    },
    {
        "company": "Hodkiewicz Inc",
        "position": "Human Resources Assistant III",
        "jobLocation": "Enonkoski",
        "jobType": "internship",
        "status": "declined",
        "createdBy": "6277c5c549827787d8250ed2",
        "createdAt": "2020-02-20T05:13:35Z"
    },
    {
        "company": "Hills-Nitzsche",
        "position": "Human Resources Manager",
        "jobLocation": "Pingwang",
        "jobType": "remote",
        "status": "interview",
        "createdBy": "6277c5c549827787d8250ed2",
        "createdAt": "2020-06-20T17:09:32Z"
    },
    {
        "company": "Greenfelder, Harvey and Franecki",
        "position": "Administrative Officer",
        "jobLocation": "Chitose",
        "jobType": "remote",
        "status": "pending",
        "createdBy": "6277c5c549827787d8250ed2",
        "createdAt": "2020-11-11T20:21:00Z"
    },
    {
        "company": "Davis, Predovic and Turcotte",
        "position": "Accountant IV",
        "jobLocation": "Famões",
        "jobType": "remote",
        "status": "pending",
        "createdBy": "6277c5c549827787d8250ed2",
        "createdAt": "2019-11-16T10:57:28Z"
    },
    {
        "company": "Hand, Grimes and Medhurst",
        "position": "Help Desk Technician",
        "jobLocation": "Zhengcun",
        "jobType": "part-time",
        "status": "declined",
        "createdBy": "6277c5c549827787d8250ed2",
        "createdAt": "2022-03-30T22:56:08Z"
    },
    {
        "company": "Gerlach, Schimmel and Johnston",
        "position": "Electrical Engineer",
        "jobLocation": "Inicbulan",
        "jobType": "remote",
        "status": "declined",
        "createdBy": "6277c5c549827787d8250ed2",
        "createdAt": "2020-01-21T22:19:47Z"
    },
    {
        "company": "Baumbach, Wuckert and Schmidt",
        "position": "Speech Pathologist",
        "jobLocation": "Monte Mor",
        "jobType": "full-time",
        "status": "declined",
        "createdBy": "6277c5c549827787d8250ed2",
        "createdAt": "2019-10-14T15:29:34Z"
    },
    {
        "company": "Treutel Group",
        "position": "Social Worker",
        "jobLocation": "Strasbourg",
        "jobType": "part-time",
        "status": "pending",
        "createdBy": "6277c5c549827787d8250ed2",
        "createdAt": "2021-01-17T07:16:00Z"
    },
    {
        "company": "Donnelly, Schuster and Skiles",
        "position": "Environmental Specialist",
        "jobLocation": "Grand Bois",
        "jobType": "part-time",
        "status": "interview",
        "createdBy": "6277c5c549827787d8250ed2",
        "createdAt": "2022-01-20T11:35:13Z"
    },
    {
        "company": "Kassulke-Parisian",
        "position": "Director of Sales",
        "jobLocation": "Mayahi",
        "jobType": "remote",
        "status": "pending",
        "createdBy": "6277c5c549827787d8250ed2",
        "createdAt": "2020-07-30T17:30:29Z"
    },
    {
        "company": "Bins and Sons",
        "position": "Software Test Engineer IV",
        "jobLocation": "Shirbīn",
        "jobType": "full-time",
        "status": "interview",
        "createdBy": "6277c5c549827787d8250ed2",
        "createdAt": "2020-07-17T15:21:20Z"
    },
    {
        "company": "Gerhold Group",
        "position": "Programmer Analyst II",
        "jobLocation": "Haolibao",
        "jobType": "internship",
        "status": "pending",
        "createdBy": "6277c5c549827787d8250ed2",
        "createdAt": "2021-10-11T11:42:27Z"
    },
    {
        "company": "Sawayn LLC",
        "position": "Pharmacist",
        "jobLocation": "Kulevcha",
        "jobType": "part-time",
        "status": "interview",
        "createdBy": "6277c5c549827787d8250ed2",
        "createdAt": "2020-08-29T13:32:44Z"
    },
    {
        "company": "Pollich-Kub",
        "position": "Human Resources Manager",
        "jobLocation": "Tigbaw",
        "jobType": "remote",
        "status": "pending",
        "createdBy": "6277c5c549827787d8250ed2",
        "createdAt": "2021-08-06T19:33:42Z"
    },
    {
        "company": "Glover Group",
        "position": "Librarian",
        "jobLocation": "Bonga",
        "jobType": "internship",
        "status": "interview",
        "createdBy": "6277c5c549827787d8250ed2",
        "createdAt": "2020-05-04T20:47:24Z"
    },
    {
        "company": "Wisoky LLC",
        "position": "Operator",
        "jobLocation": "Żórawina",
        "jobType": "remote",
        "status": "interview",
        "createdBy": "6277c5c549827787d8250ed2",
        "createdAt": "2020-05-01T23:58:25Z"
    },
    {
        "company": "Wunsch-Waters",
        "position": "Physical Therapy Assistant",
        "jobLocation": "Aurillac",
        "jobType": "remote",
        "status": "pending",
        "createdBy": "6277c5c549827787d8250ed2",
        "createdAt": "2020-03-27T19:45:43Z"
    },
    {
        "company": "Johns Inc",
        "position": "Automation Specialist I",
        "jobLocation": "Kangshan",
        "jobType": "internship",
        "status": "interview",
        "createdBy": "6277c5c549827787d8250ed2",
        "createdAt": "2021-03-16T17:32:05Z"
    },
    {
        "company": "Bahringer and Sons",
        "position": "Budget/Accounting Analyst III",
        "jobLocation": "Partido",
        "jobType": "internship",
        "status": "declined",
        "createdBy": "6277c5c549827787d8250ed2",
        "createdAt": "2019-07-24T11:09:16Z"
    },
    {
        "company": "Beier-Stokes",
        "position": "Office Assistant III",
        "jobLocation": "Chlumec nad Cidlinou",
        "jobType": "internship",
        "status": "pending",
        "createdBy": "6277c5c549827787d8250ed2",
        "createdAt": "2022-03-18T10:40:25Z"
    },
    {
        "company": "Walter, Huel and Pacocha",
        "position": "VP Sales",
        "jobLocation": "Zaliznychne",
        "jobType": "remote",
        "status": "pending",
        "createdBy": "6277c5c549827787d8250ed2",
        "createdAt": "2021-10-30T12:34:18Z"
    },
    {
        "company": "Legros, Rath and Ledner",
        "position": "Executive Secretary",
        "jobLocation": "Aegela",
        "jobType": "remote",
        "status": "interview",
        "createdBy": "6277c5c549827787d8250ed2",
        "createdAt": "2021-09-12T20:46:09Z"
    },
    {
        "company": "Windler-Dibbert",
        "position": "Marketing Manager",
        "jobLocation": "Imtarfa",
        "jobType": "full-time",
        "status": "interview",
        "createdBy": "6277c5c549827787d8250ed2",
        "createdAt": "2021-01-02T04:49:00Z"
    },
    {
        "company": "Swaniawski, Toy and Heaney",
        "position": "Account Representative I",
        "jobLocation": "Privolzhskiy",
        "jobType": "remote",
        "status": "interview",
        "createdBy": "6277c5c549827787d8250ed2",
        "createdAt": "2020-11-18T16:15:51Z"
    },
    {
        "company": "Schimmel LLC",
        "position": "Technical Writer",
        "jobLocation": "Garunggang",
        "jobType": "part-time",
        "status": "interview",
        "createdBy": "6277c5c549827787d8250ed2",
        "createdAt": "2021-09-12T15:43:07Z"
    },
    {
        "company": "Breitenberg, Waters and Hansen",
        "position": "Nuclear Power Engineer",
        "jobLocation": "Xiuying",
        "jobType": "full-time",
        "status": "pending",
        "createdBy": "6277c5c549827787d8250ed2",
        "createdAt": "2020-05-16T08:02:27Z"
    },
    {
        "company": "Kiehn-Simonis",
        "position": "Quality Engineer",
        "jobLocation": "Bakar",
        "jobType": "internship",
        "status": "declined",
        "createdBy": "6277c5c549827787d8250ed2",
        "createdAt": "2019-09-08T18:45:26Z"
    },
    {
        "company": "Bailey-Balistreri",
        "position": "Registered Nurse",
        "jobLocation": "Bulbul",
        "jobType": "full-time",
        "status": "pending",
        "createdBy": "6277c5c549827787d8250ed2",
        "createdAt": "2020-02-14T07:57:18Z"
    },
    {
        "company": "Schowalter Group",
        "position": "Staff Scientist",
        "jobLocation": "Port Sudan",
        "jobType": "part-time",
        "status": "interview",
        "createdBy": "6277c5c549827787d8250ed2",
        "createdAt": "2019-11-22T21:12:55Z"
    },
    {
        "company": "Ondricka, Weimann and Monahan",
        "position": "Electrical Engineer",
        "jobLocation": "Talibura",
        "jobType": "internship",
        "status": "declined",
        "createdBy": "6277c5c549827787d8250ed2",
        "createdAt": "2020-01-18T16:45:52Z"
    },
    {
        "company": "Legros, Jerde and Rath",
        "position": "Physical Therapy Assistant",
        "jobLocation": "Oborniki Śląskie",
        "jobType": "internship",
        "status": "interview",
        "createdBy": "6277c5c549827787d8250ed2",
        "createdAt": "2021-01-29T06:35:51Z"
    },
    {
        "company": "Swaniawski-Schimmel",
        "position": "Graphic Designer",
        "jobLocation": "Passos",
        "jobType": "internship",
        "status": "interview",
        "createdBy": "6277c5c549827787d8250ed2",
        "createdAt": "2020-09-12T23:35:19Z"
    }
]